constantcontact/__init__.py
constantcontact/accountservice.py
constantcontact/activityservice.py
constantcontact/baseservice.py
constantcontact/constantcontact.py
constantcontact/contactservice.py
constantcontact/emailmarketingservice.py
constantcontact/eventspotservice.py
constantcontact/listservice.py
constantcontact/mylibraryservice.py
constantcontact/partnerservice.py
constantcontact/components/__init__.py
constantcontact/components/account_info.py
constantcontact/components/activity_report.py
constantcontact/components/activity_status.py
constantcontact/components/address.py
constantcontact/components/attribute.py
constantcontact/components/billing_plan.py
constantcontact/components/campaign.py
constantcontact/components/contact.py
constantcontact/components/contact_list.py
constantcontact/components/domain_lambda.py
constantcontact/components/email_address.py
constantcontact/components/event.py
constantcontact/components/fee.py
constantcontact/components/item.py
constantcontact/components/multipart_activity.py
constantcontact/components/multipart_file.py
constantcontact/components/mylibrary_file.py
constantcontact/components/mylibrary_folder.py
constantcontact/components/partner_account.py
constantcontact/components/promocode.py
constantcontact/components/registrant.py
constantcontact/components/result_set.py
constantcontact/components/schedule.py
constantcontact/components/tracking_summary.py
constantcontact-0.3.4.dist-info/METADATA
constantcontact-0.3.4.dist-info/RECORD
constantcontact-0.3.4.dist-info/WHEEL
constantcontact-0.3.4.dist-info/top_level.txt
