Metadata-Version: 2.1
Name: constantcontact
Version: 0.3.4
Summary: A Python SDK for the Constant Contact v2 API
Home-page: http://developer.constantcontact.com/libraries/libraries.html
Author: Constant Contact Inc.
Author-email: UNKNOWN
License: MIT
Keywords: constantcontact sdk
Platform: UNKNOWN
Classifier: Development Status :: 3 - Alpha
Classifier: Intended Audience :: Developers
Classifier: Natural Language :: English
Classifier: License :: OSI Approved :: MIT License
Classifier: Programming Language :: Python :: 2
Classifier: Programming Language :: Python :: 2.6
Classifier: Programming Language :: Python :: 2.7
Classifier: Programming Language :: Python :: 3
Classifier: Programming Language :: Python :: 3.3
Classifier: Programming Language :: Python :: 3.4
Requires-Dist: requests
